cardinal/__init__.py
cardinalmsi-0.0.0.dist-info/LICENSE
cardinalmsi-0.0.0.dist-info/METADATA
cardinalmsi-0.0.0.dist-info/WHEEL
cardinalmsi-0.0.0.dist-info/top_level.txt
cardinalmsi-0.0.0.dist-info/RECORD
