Metadata-Version: 2.1
Name: cardinalmsi
Version: 0.0.0
Summary: Python interface for R/Bioconductor 'Cardinal' package (under development)
Author-email: "Kylie A. Bemis" <k.bemis@northeastern.edu>
License: Artistic License 2.0
Classifier: Development Status :: 1 - Planning
Classifier: Programming Language :: Python :: 3
Classifier: License :: OSI Approved :: Artistic License
Classifier: Intended Audience :: Science/Research
Requires-Python: >=3.10
License-File: LICENSE
